PyBambooHR/PyBambooHR.py
PyBambooHR/__init__.py
PyBambooHR/config.py
PyBambooHR/utils.py
PyBambooHR-0.8.1.dist-info/AUTHORS
PyBambooHR-0.8.1.dist-info/LICENSE
PyBambooHR-0.8.1.dist-info/METADATA
PyBambooHR-0.8.1.dist-info/WHEEL
PyBambooHR-0.8.1.dist-info/top_level.txt
PyBambooHR-0.8.1.dist-info/RECORD
