Metadata-Version: 2.1
Name: PyBambooHR
Version: 0.8.1
Summary: A Python wrapper for the Bamboo HR API
Home-page: http://github.com/smeggingsmegger/PyBambooHR
Author: Scott Blevins
Author-email: sblevins@gmail.com
License: MIT
Keywords: Bamboo,HR,BambooHR,API
Platform: OS Independent
Classifier: Development Status :: 3 - Alpha
Classifier: License :: OSI Approved :: MIT License
Classifier: Operating System :: OS Independent
Classifier: Programming Language :: Python :: 2.7
Classifier: Intended Audience :: Developers
Classifier: Topic :: Software Development :: Libraries :: Python Modules
Requires-Dist: requests
Requires-Dist: xmltodict
